{
    "Rusd" : 73.49,
    "Reur" : 79.57,
    "Rbyn" : 30.08,
    "Ruan" : 2.74,
    "Rpln" : 17.43,

    "Urub" : 73.49,
    "Ueur" : 0.92,
    "Ubyn" : 2.44,
    "Uuan" : 26.72,
    "Upln" : 4.20,

    "Erub" : 79.63,
    "Eusd" : 1.09,
    "Ebyn" : 2.65,
    "Euan" : 29.01,
    "Epln" : 4.56,

    "Brub" : 30.09,
    "Busd" : 2.44,
    "Beur" : 2.65,
    "Buan" : 10.96,
    "Bpln" : 1.72,

    "Uarub" : 2.74,
    "Uausd" : 26.72,
    "Uaeur" : 29.01,
    "Uabyn" : 10.96,
    "Uapln" : 0.16,

    "Prub" : 17.43,
    "Pusd" : 4.20,
    "Peur" : 4.56,
    "Pbyn" : 1.72,
    "Puan" : 0.16



}